{
  "url": "https://www.topcv.vn/viec-lam/ke-toan-tong-hop/1662714.html?ta_source=JobSearchList_LinkDetail&u_sr_id=G0QSeAlC649aTy1xO3u9WdPkOkZBldhYFCqJuhYT_1746642293",
  "title": "Kế Toán Tổng Hợp",
  "salary": "7 - 9 triệu",
  "location": "Hà Nội",
  "experience": "Dưới 1 năm",
  "company_name": "CÔNG TY CỔ PHẦN GIẢI PHÁP ĐÔNG DƯƠNG",
  "job_description": "Kiểm tra, đối chiếu số liệu kế toán, đảm bảo tính chính xác và minh bạch.\nThu thập và xử lý các số liệu liên quan đến các hoạt động kinh tế phát sinh của doanh nghiệp, bao gồm hoá đơn, phiếu thu, chi, phiếu nhập, xuất...\nHạch toán thu nhập, khấu hao, chi phí, tài sản cố định (TSCĐ), công nợ, thuế GTGT và các nghiệp vụ kế toán khác.\nTheo dõi, quản lý công nợ, đảm bảo sự ổn định tài chính của công ty.\nLưu trữ và quản lý các sổ sách, chứng từ kế toán của công ty một cách khoa học và dễ dàng tra cứu.\nThực hiện các công việc khác theo yêu cầu của cấp trên.",
  "requirements": "Tốt nghiệp chuyên ngành kế toán.\nSử dụng thành thạo máy tính.\nCẩn thận, trung thực, ham học hỏi, giao tiếp tốt.",
  "career_tags": [
    "Kế toán/Kiểm toán/Thuế",
    "Kế toán",
    "Kế toán tổng hợp",
    "Phân Tích Báo Cáo Tài Chính",
    "Lập Báo Cáo Tài Chính",
    "Kiến Thức Kế Toán Tổng Hợp",
    "Thành Thạo Phần Mềm Kế Toán (ví Dụ: Misa, Fast Accounting, Sap)",
    "Kiểm Tra Tính Chính Xác Của Dữ Liệu Kế Toán"
  ]
}